traceai_langchain/__init__.py
traceai_langchain/_tracer.py
traceai_langchain/package.py
traceai_langchain/version.py
traceai_langchain-0.1.11.dist-info/METADATA
traceai_langchain-0.1.11.dist-info/WHEEL
traceai_langchain-0.1.11.dist-info/RECORD
