Metadata-Version: 2.3
Name: traceAI-langchain
Version: 0.1.11
Summary: OpenTelemetry instrumentation for Langchain
Author: Future AGI
Author-email: no-reply@futureagi.com
Requires-Python: >3.9,<3.14
Classifier: Programming Language :: Python :: 3
Classifier: Programming Language :: Python :: 3.10
Classifier: Programming Language :: Python :: 3.11
Classifier: Programming Language :: Python :: 3.12
Classifier: Programming Language :: Python :: 3.13
Requires-Dist: fi-instrumentation-otel (>=0.1.11)
Requires-Dist: langchain-community[all] (>=0.3.9,<0.4.0)
Requires-Dist: langchain-core (>=0.2.43)
Requires-Dist: langchain[all] (>=0.3.9,<0.4.0)
